esper_tool/__init__.py
esper_tool/__main__.py
esper_tool/esper.py
esper_tool/version.py
esper_tool-1.3.2.dist-info/LICENSE
esper_tool-1.3.2.dist-info/METADATA
esper_tool-1.3.2.dist-info/WHEEL
esper_tool-1.3.2.dist-info/entry_points.txt
esper_tool-1.3.2.dist-info/top_level.txt
esper_tool-1.3.2.dist-info/RECORD
