Metadata-Version: 2.1
Name: esper-tool
Version: 1.3.2
Summary: Command line tool for accessing ESPER
Home-page: https://github.com/bryerton/esper-tool
Author: Bryerton Shaw
Author-email: bryerton@triumf.ca
License: MIT
Keywords: esper monitoring control experiments
Platform: UNKNOWN
Classifier: Development Status :: 5 - Production/Stable
Classifier: Intended Audience :: Science/Research
Classifier: Environment :: Console
Classifier: Topic :: System :: Networking
Classifier: License :: OSI Approved :: MIT License
Classifier: Programming Language :: Python :: 2
Classifier: Programming Language :: Python :: 2.7
Classifier: Programming Language :: Python :: 3
Classifier: Programming Language :: Python :: 3.3
Classifier: Programming Language :: Python :: 3.4
Classifier: Programming Language :: Python :: 3.5
License-File: LICENSE
Requires-Dist: requests
Requires-Dist: argparse
Requires-Dist: future
Requires-Dist: numpy
